html_cleaner_kinship/__init__.py
html_cleaner_kinship/cleaner.py
html_cleaner_kinship/io.py
html_cleaner_kinship/utils.py
html_cleaner_kinship-0.2.dist-info/METADATA
html_cleaner_kinship-0.2.dist-info/WHEEL
html_cleaner_kinship-0.2.dist-info/RECORD
